{"cameraMode":{"drawMode":0,"name":"Shaded","section":"Shading Mode"},"sceneLighting":true,"audioPlay":false,"sceneViewState":{"m_AlwaysRefresh":false,"showFog":true,"showSkybox":true,"showFlares":true,"showImageEffects":true,"showParticleSystems":true,"showVisualEffectGraphs":true,"m_FxEnabled":true},"in2DMode":false,"pivot":{"x":72.21549224853516,"y":313.091064453125,"z":-4.581727981567383},"rotation":{"x":-0.0366024449467659,"y":0.8857110738754273,"z":-0.07082679122686386,"w":-0.45739737153053286},"size":561.2511596679688,"orthographic":false}